vdrnn/__init__.py
vdrnn/model_lstm.py
vdrnn/vrnn.py
vdrnn-0.1.dist-info/METADATA
vdrnn-0.1.dist-info/WHEEL
vdrnn-0.1.dist-info/top_level.txt
vdrnn-0.1.dist-info/RECORD
