Metadata-Version: 2.1
Name: vdrnn
Version: 0.1
Summary: implementation of variational recurrent neural networks for learning curve prediction
Home-page: UNKNOWN
Author: Matilde Gargiani
Author-email: matildegargiani@gmail.com
License: MIT
Platform: UNKNOWN
Requires-Dist: ConfigSpace
Requires-Dist: torch
Requires-Dist: hpbandster
